{
    "err_code": 0,
    "err_msg": "success",
    "data": [
        {"uid":1,"username":"张三","filename":"http://lorempixel.com/68/68/people/1/","spell":"☆"},
        {"uid":2,"username":"张四","filename":"http://lorempixel.com/68/68/people/2/","spell":"☆"},
        {"uid":3,"username":"张五","filename":"http://lorempixel.com/68/68/people/3/","spell":"☆"},
        {"uid":4,"username":"张六","filename":"http://lorempixel.com/68/68/people/4/","spell":"☆"},
        {"uid":5,"username":"张七","filename":"http://lorempixel.com/68/68/people/5/","spell":"☆"},
        {"uid":6,"username":"张俆","filename":"http://lorempixel.com/68/68/people/6/","spell":"☆"},
        {"uid":7,"username":"张九","filename":"http://lorempixel.com/68/68/people/7/","spell":"☆"},
        {"uid":8,"username":"张十","filename":"http://lorempixel.com/68/68/people/8/","spell":"☆"},
        {"uid":9,"username":"Alex Clack","filename":"http://lorempixel.com/68/68/people/8/","spell":"A"},
        {"uid":10,"username":"Alex Black","filename":"http://lorempixel.com/68/68/people/5/","spell":"A"},
        {"uid":11,"username":"Alex Proti","filename":"http://lorempixel.com/68/68/people/3/","spell":"A"},
        {"uid":12,"username":"Andrew Smith","filename":"http://lorempixel.com/68/68/people/5/","spell":"A"},
        {"uid":13,"username":"Ann Ryder","filename":"http://lorempixel.com/68/68/people/5/","spell":"A"},
        {"uid":14,"username":"Daniel Ricci","filename":"http://lorempixel.com/68/68/people/5/","spell":"D"},
        {"uid":15,"username":"Ivan Ivanov","filename":"http://lorempixel.com/68/68/people/3/","spell":"I"},
        {"uid":16,"username":"Ivan Black","filename":"http://lorempixel.com/68/68/people/6/","spell":"I"},
        {"uid":17,"username":"Kate Lebedeva","filename":"http://lorempixel.com/68/68/people/3/","spell":"K"},
        {"uid":18,"username":"Kate Shy","filename":"http://lorempixel.com/68/68/people/6/","spell":"K"},
        {"uid":19,"username":"Michael Fold","filename":"http://lorempixel.com/68/68/people/6/","spell":"M"},
        {"uid":20,"username":"Michael Black","filename":"http://lorempixel.com/68/68/people/3/","spell":"M"},
        {"uid":21,"username":"Nadya Black","filename":"http://lorempixel.com/68/68/people/3/","spell":"N"},
        {"uid":22,"username":"Nadya Price","filename":"http://lorempixel.com/68/68/people/8/","spell":"N"},
        {"uid":23,"username":"Nadya Oleg","filename":"http://lorempixel.com/68/68/people/3/","spell":"N"},
        {"uid":24,"username":"Oleg Black","filename":"http://lorempixel.com/68/68/people/3/","spell":"O"},
        {"uid":25,"username":"Oleg Price","filename":"http://lorempixel.com/68/68/people/6/","spell":"O"},
        {"uid":26,"username":"Oleg Oleg","filename":"http://lorempixel.com/68/68/people/3/","spell":"O"},
        {"uid":27,"username":"Svetlana Kot","avatar":"http://lorempixel.com/68/68/people/10/","spell":"S"}
        
        
    ]
}